secret/SCRATCH.py
secret/__init__.py
tests/__init__.py
tests/__main__.py
viewable/__init__.py
viewable/__main__.py
viewable/error/__init__.py
viewable/hooking/__init__.py
viewable/hooking/ante_build_hook.py
viewable/hooking/ante_release_hook.py
viewable/hooking/post_build_hook.py
viewable/hooking/post_release_hook.py
viewable/pyrustic_data/hooking.json
viewable/pyrustic_data/hubstore.json
viewable/pyrustic_data/release_info.json
viewable/pyrustic_data/backstage/config/build.json
viewable/pyrustic_data/backstage/config/init.json
viewable/pyrustic_data/backstage/config/release.json
viewable/pyrustic_data/backstage/data/build_report.json
viewable/pyrustic_data/backstage/data/github_release_form.json
viewable/pyrustic_data/backstage/hooking/build.json
viewable/pyrustic_data/backstage/hooking/init.json
viewable/pyrustic_data/backstage/hooking/release.json
viewable/pyrustic_data/backstage/report/build_report.json
viewable/pyrustic_data/backstage/report/release_report.json
viewable/pyrustic_data/hubstore/img.json
viewable/pyrustic_data/hubstore/promotion.json
viewable-0.0.7.dist-info/LICENSE
viewable-0.0.7.dist-info/METADATA
viewable-0.0.7.dist-info/WHEEL
viewable-0.0.7.dist-info/entry_points.txt
viewable-0.0.7.dist-info/top_level.txt
viewable-0.0.7.dist-info/RECORD
