Metadata-Version: 2.1
Name: viewable
Version: 0.0.7
Summary: Python library to implement a GUI view with lifecycle
Home-page: https://github.com/pyrustic/viewable
Author: Pyrustic Evangelist
Author-email: rusticalex@yahoo.com
Maintainer: Pyrustic Evangelist
Maintainer-email: rusticalex@yahoo.com
License: MIT
Keywords: library,frontend,view,gui,tkinter,view-lifecycle,lifecycle,desktop-application,pyrustic
Platform: UNKNOWN
Classifier: Programming Language :: Python :: 3
Classifier: License :: OSI Approved :: MIT License
Classifier: Operating System :: OS Independent
Requires-Python: >=3.5
License-File: LICENSE
